{"source/aam-main.ptx": ["AAM"], "source/aam_frontmatter.ptx": ["frontmatter", "AAM-fm-col", "AAM-fm-ack"], "source/ch_intro.ptx": ["ch-intro"], "source/sec_intro_mst.ptx": ["sec-intro-mst"], "source/sec_intro_kidrsa.ptx": ["sec-intro-kidrsa"], "source/ch_perms.ptx": ["ch-perms"], "source/sec_perms_def.ptx": ["sec-perms-def"], "source/sec_perms_oop.ptx": ["sec-perms-oop"], "source/ch_crypto.ptx": ["ch-crypto"], "source/sec_crypto_simple.ptx": ["sec-crypto-subst"], "source/sec_crypto_classic.ptx": ["sec-crypto-classic"], "source/sec_crypto_proj.ptx": ["sec-crypto-proj"], "source/ch_linalg.ptx": ["ch-linalg"], "source/sec_linalg_vectors.ptx": ["sec-linalg-vectors"], "source/sec_linalg_vecproj.ptx": ["sec-linalg-vecproj"], "source/sec_linalg_matrices.ptx": ["sec-linalg-matrices"], "source/sec_linalg_matproj.ptx": ["sec-linalg-matproj"], "source/ch_matapps.ptx": ["ch-matrix-apps"], "source/sec_matapps_ssles.ptx": ["sec-matapps-ssles"], "source/sec_matapps_gjepp.ptx": ["sec-matapps-gje_proj"], "source/sec_matapps_ludecomp.ptx": ["sec-matapps-ludecomp"], "source/ch_gtalgos.ptx": ["ch-gtalgos"], "source/sec_gtalgos_basics.ptx": ["sec-gtalgos-basics"], "source/sec_gtalgos_mst.ptx": ["sec-gtalgos-mst"], "source/sec_gtalgos_shortestpath.ptx": ["sec-gtalgos-shortestpath"], "source/sec_gtalgos_maxflowmincut.ptx": ["sec-gtalgos-maxflowmincut"], "source/aam_backmatter.ptx": ["aam-backmatter"], "source/app_python.ptx": ["app-python"], "source/appsec_python_idle.ptx": ["sec-intro-idle"], "source/appsec_python_basicdata.ptx": ["sec-intro_basicdata"], "source/appsec_python_containers.ptx": ["sec-intro-containers"], "source/appsec_python_iteration.ptx": ["sec-intro-iteration"], "source/appsec_python_functions.ptx": ["sec-intro-functions"], "source/appsec_python_errors.ptx": ["sec-intro-errors"], "source/app_lists.ptx": ["appendix-lists", "app-find-defs", "app-find-tech", "app-find-results", "app-find-projects"], "source/gfdl-aam.ptx": ["appendix-gfdl"]}